demo/__init__.py
demo/local_settings.py
demo/sass_variables.py
demo/settings.py
demo/urls.py
demo/views.py
demo/wsgi.py
psu_base/__init__.py
psu_base/admin.py
psu_base/apps.py
psu_base/context_processors.py
psu_base/decorators.py
psu_base/urls.py
psu_base/classes/Auth.py
psu_base/classes/BannerDowntime.py
psu_base/classes/ConvenientDate.py
psu_base/classes/DynamicRole.py
psu_base/classes/Encryptor.py
psu_base/classes/Faki.py
psu_base/classes/Finti.py
psu_base/classes/IdentityCAS.py
psu_base/classes/IdentitySearch.py
psu_base/classes/Log.py
psu_base/classes/Term.py
psu_base/classes/User.py
psu_base/classes/__init__.py
psu_base/fixtures/__init__.py
psu_base/interceptors/__init__.py
psu_base/interceptors/psu_base_interceptor_middleware.py
psu_base/interceptors/security_interceptor_middleware.py
psu_base/management/commands/aws_logs.py
psu_base/management/commands/encrypt.py
psu_base/management/commands/env_vars.py
psu_base/migrations/0001_initial.py
psu_base/migrations/0002_remove_infotext_last_updated.py
psu_base/migrations/0003_delete_infotext.py
psu_base/migrations/0004_feature.py
psu_base/migrations/0005_audit.py
psu_base/migrations/0006_auto_20190812_1805.py
psu_base/migrations/0007_auto_20190813_1122.py
psu_base/migrations/0008_adminscript.py
psu_base/migrations/0009_auto_20190822_1702.py
psu_base/migrations/0010_email.py
psu_base/migrations/0011_xss.py
psu_base/migrations/0012_fakiresponse.py
psu_base/migrations/0013_error.py
psu_base/migrations/0014_auto_20200528_1516.py
psu_base/migrations/0015_auto_20200713_0949.py
psu_base/migrations/0016_error_debug_info.py
psu_base/migrations/0017_error_browser.py
psu_base/migrations/0018_auto_20201105_1551.py
psu_base/migrations/0019_error_stacktrace.py
psu_base/migrations/0020_auto_20201216_1006.py
psu_base/migrations/0021_student.py
psu_base/migrations/0022_downtime.py
psu_base/migrations/0023_auto_20210706_1044.py
psu_base/migrations/0024_alter_audit_comments.py
psu_base/migrations/0025_student_name_updated.py
psu_base-6.3.3.dist-info/METADATA
psu_base-6.3.3.dist-info/WHEEL
psu_base-6.3.3.dist-info/top_level.txt
psu_base-6.3.3.dist-info/RECORD
